Metadata-Version: 2.1
Name: django-stripe-billing
Version: 0.5.1
Summary: Django billing plans and payments with Stripe
Home-page: https://github.com/hkhanna/django-stripe-billing
Author: Harry Khanna
Author-email: harry@khanna.cc
License: MIT
Classifier: Framework :: Django
Classifier: Programming Language :: Python
Classifier: Intended Audience :: Developers
Requires-Python: >=3.8
License-File: LICENSE
Requires-Dist: Django
Requires-Dist: stripe (==2.*)
